yanimt/__init__.py
yanimt/__main__.py
yanimt/_config.py
yanimt/_database/__init__.py
yanimt/_database/manager.py
yanimt/_database/models.py
yanimt/_dns/__init__.py
yanimt/_dns/main.py
yanimt/_ldap/__init__.py
yanimt/_ldap/main.py
yanimt/_ldap/query.py
yanimt/_smb/__init__.py
yanimt/_smb/main.py
yanimt/_smb/secrets_dump.py
yanimt/_tui/__init__.py
yanimt/_tui/computers.py
yanimt/_tui/gather.py
yanimt/_tui/groups.py
yanimt/_tui/logger.py
yanimt/_tui/ous.py
yanimt/_tui/progress.py
yanimt/_tui/tabs.py
yanimt/_tui/users.py
yanimt/_util/__init__.py
yanimt/_util/consts.py
yanimt/_util/exceptions.py
yanimt/_util/logger.py
yanimt/_util/smart_class.py
yanimt/_util/types.py
yanimt/cli/__init__.py
yanimt/cli/gather.py
yanimt/gatherer.py
yanimt/static/tcss/object_screen.tcss
yanimt-0.0.5.dist-info/METADATA
yanimt-0.0.5.dist-info/WHEEL
yanimt-0.0.5.dist-info/entry_points.txt
yanimt-0.0.5.dist-info/licenses/LICENSE
yanimt-0.0.5.dist-info/RECORD
