Metadata-Version: 2.4
Name: yanimt
Version: 0.0.5
Summary: Yet another impacket tool
License: MIT
License-File: LICENSE
Author: Headorteil
Requires-Python: >=3.11
Classifier: Environment :: Console
Classifier: License :: OSI Approved :: MIT License
Classifier: Programming Language :: Python :: 3
Classifier: Programming Language :: Python :: 3.11
Classifier: Programming Language :: Python :: 3.12
Classifier: Programming Language :: Python :: 3.13
Classifier: Programming Language :: Python :: 3.14
Classifier: Topic :: Security
Requires-Dist: dnspython (>=2.8.0,<3.0.0)
Requires-Dist: impacket (>=0.12.0,<0.13.0)
Requires-Dist: pyyaml (>=6.0.3,<7.0.0)
Requires-Dist: rich (>=14.1.0,<15.0.0)
Requires-Dist: sqlalchemy (>=2.0.43,<3.0.0)
Requires-Dist: textual (>=6.2.1,<7.0.0)
Requires-Dist: typer (>=0.19.2,<0.20.0)
Project-URL: Homepage, https://github.com/Headorteil/yanimt
Project-URL: Repository, https://github.com/Headorteil/yanimt
